{
    "sofa": [
        {
            "name": "Карточка 1",
            "image": "/1.png",
            "date": "2022-03-06"
        },
        {
            "name": "Карточка 2",
            "image": "/2.png",
            "date": "2022-02-06"
        },
        {
            "name": "Карточка 3",
            "image": "/3.png",
            "date": "2022-08-06"
        },
        {
            "name": "Карточка 4",
            "image": "/4.png",
            "date": "2022-01-06"
        },
        {
            "name": "Карточка 5",
            "image": "/5.png",
            "date": "2022-01-06"
        },
        {
            "name": "Карточка 6",
            "image": "/6.png",
            "date": "2022-01-06"
        },
        {
            "name": "Карточка 7",
            "image": "/6.png",
            "date": "2022-01-06"
        },
        {
            "name": "Карточка 8",
            "image": "/6.png",
            "date": "2022-01-06"
        },
        {
            "name": "Карточка 9",
            "image": "/6.png",
            "date": "2022-01-06"
        },
        {
            "name": "Карточка 10",
            "image": "/6.png",
            "date": "2022-01-06"
        }
    ],
    "chair": [
        {
            "name": "Карточка 1",
            "image": "/1.png",
            "date": "2022-03-06"
        },
        {
            "name": "Карточка 2",
            "image": "/2.png",
            "date": "2022-02-06"
        },
        {
            "name": "Карточка 3",
            "image": "/3.png",
            "date": "2022-08-06"
        },
        {
            "name": "Карточка 4",
            "image": "/4.png",
            "date": "2022-01-06"
        },
        {
            "name": "Карточка 5",
            "image": "/5.png",
            "date": "2022-01-06"
        },
        {
            "name": "Карточка 6",
            "image": "/6.png",
            "date": "2022-01-06"
        },
        {
            "name": "Карточка 7",
            "image": "/6.png",
            "date": "2022-01-06"
        },
        {
            "name": "Карточка 8",
            "image": "/6.png",
            "date": "2022-01-06"
        },
        {
            "name": "Карточка 9",
            "image": "/6.png",
            "date": "2022-01-06"
        },
        {
            "name": "Карточка 10",
            "image": "/6.png",
            "date": "2022-01-06"
        }
    ],
    "table": [
        {
            "name": "Карточка 1",
            "image": "/1.png",
            "date": "2022-03-06"
        },
        {
            "name": "Карточка 2",
            "image": "/2.png",
            "date": "2022-02-06"
        },
        {
            "name": "Карточка 3",
            "image": "/3.png",
            "date": "2022-08-06"
        },
        {
            "name": "Карточка 4",
            "image": "/4.png",
            "date": "2022-01-06"
        },
        {
            "name": "Карточка 5",
            "image": "/5.png",
            "date": "2022-01-06"
        },
        {
            "name": "Карточка 6",
            "image": "/6.png",
            "date": "2022-01-06"
        },
        {
            "name": "Карточка 7",
            "image": "/6.png",
            "date": "2022-01-06"
        },
        {
            "name": "Карточка 8",
            "image": "/6.png",
            "date": "2022-01-06"
        },
        {
            "name": "Карточка 9",
            "image": "/6.png",
            "date": "2022-01-06"
        },
        {
            "name": "Карточка 10",
            "image": "/6.png",
            "date": "2022-01-06"
        }
    ]
}